acumos_model_runner/__init__.py
acumos_model_runner/_version.py
acumos_model_runner/api.py
acumos_model_runner/oas_gen.py
acumos_model_runner/proto_parser.py
acumos_model_runner/runner.py
acumos_model_runner/utils.py
acumos_model_runner/data/proto3.ebnf
acumos_model_runner/data/templates/0.6.0/base.yaml
acumos_model_runner/data/templates/0.6.0/method.yaml
acumos_model_runner-0.2.6.dist-info/LICENSE.txt
acumos_model_runner-0.2.6.dist-info/METADATA
acumos_model_runner-0.2.6.dist-info/WHEEL
acumos_model_runner-0.2.6.dist-info/entry_points.txt
acumos_model_runner-0.2.6.dist-info/top_level.txt
acumos_model_runner-0.2.6.dist-info/RECORD
