Metadata-Version: 2.1
Name: acumos-model-runner
Version: 0.2.6
Summary: Acumos model runner for Python models
Home-page: https://gerrit.acumos.org/r/gitweb?p=python-model-runner.git
Author: Paul Triantafyllou, Eric Zavesky
Author-email: trianta@research.att.com, ezavesky@research.att.com
License: Apache License 2.0
Keywords: acumos machine learning model runner server protobuf ml ai
Platform: UNKNOWN
Classifier: Development Status :: 4 - Beta
Classifier: Intended Audience :: Developers
Classifier: Intended Audience :: Science/Research
Classifier: Programming Language :: Python :: 3
Classifier: Programming Language :: Python :: 3.6
Classifier: License :: OSI Approved :: Apache Software License
Requires-Python: >=3.6
Requires-Dist: acumos (>=0.9.7)
Requires-Dist: lark-parser (<0.8)
Requires-Dist: connexion[swagger-ui] (~=2.6)
Requires-Dist: gunicorn
Requires-Dist: pyyaml
Requires-Dist: jinja2
Requires-Dist: protobuf
Requires-Dist: flask-cors
